x402_connector/__init__.py
x402_connector/core/__init__.py
x402_connector/core/adapters.py
x402_connector/core/config.py
x402_connector/core/context.py
x402_connector/core/facilitators.py
x402_connector/core/processor.py
x402_connector/core/facilitators/__init__.py
x402_connector/core/facilitators/corbits.py
x402_connector/core/facilitators/hybrid.py
x402_connector/core/facilitators/local.py
x402_connector/core/facilitators/payai.py
x402_connector/django/__init__.py
x402_connector/django/adapter.py
x402_connector/django/decorators.py
x402_connector/django/middleware.py
x402_connector/fastapi/__init__.py
x402_connector/fastapi/adapter.py
x402_connector/fastapi/decorators.py
x402_connector/fastapi/middleware.py
x402_connector/flask/__init__.py
x402_connector/flask/adapter.py
x402_connector/flask/decorators.py
x402_connector/flask/middleware.py
x402_connector/pyramid/__init__.py
x402_connector/pyramid/adapter.py
x402_connector/pyramid/decorators.py
x402_connector/pyramid/middleware.py
x402_connector/tornado/__init__.py
x402_connector/tornado/adapter.py
x402_connector/tornado/decorators.py
x402_connector/tornado/middleware.py
x402_connector-0.1.0.dist-info/METADATA
x402_connector-0.1.0.dist-info/WHEEL
x402_connector-0.1.0.dist-info/licenses/LICENSE
x402_connector-0.1.0.dist-info/RECORD
