Metadata-Version: 2.4
Name: x402-connector
Version: 0.1.0
Summary: Universal Python SDK for the x402 Payment Required protocol
Project-URL: Homepage, https://github.com/borchain/x402-connector
Project-URL: Documentation, https://x402-connector.readthedocs.io
Project-URL: Repository, https://github.com/borchain/x402-connector
Project-URL: Issues, https://github.com/borchain/x402-connector/issues
Author: x402 Contributors
License: MIT
License-File: LICENSE
Keywords: base,cryptocurrency,http402,payments,solana,web3,x402
Classifier: Development Status :: 4 - Beta
Classifier: Framework :: Django
Classifier: Framework :: FastAPI
Classifier: Framework :: Flask
Classifier: Framework :: Pyramid
Classifier: Intended Audience :: Developers
Classifier: License :: OSI Approved :: MIT License
Classifier: Operating System :: OS Independent
Classifier: Programming Language :: Python :: 3
Classifier: Programming Language :: Python :: 3.10
Classifier: Programming Language :: Python :: 3.11
Classifier: Programming Language :: Python :: 3.12
Classifier: Programming Language :: Python :: 3.13
Classifier: Topic :: Software Development :: Libraries :: Python Modules
Requires-Python: >=3.10
Requires-Dist: eth-account>=0.13.4
Requires-Dist: httpx>=0.27.0
Requires-Dist: requests>=2.31.0
Requires-Dist: web3>=6.20.0
Requires-Dist: x402>=0.1.0
Provides-Extra: all
Requires-Dist: django>=5.0; extra == 'all'
Requires-Dist: fastapi>=0.100.0; extra == 'all'
Requires-Dist: flask>=3.0; extra == 'all'
Requires-Dist: pyramid>=2.0; extra == 'all'
Requires-Dist: tornado>=6.0; extra == 'all'
Requires-Dist: uvicorn>=0.24.0; extra == 'all'
Requires-Dist: waitress>=2.1.2; extra == 'all'
Provides-Extra: dev
Requires-Dist: black>=23.0; extra == 'dev'
Requires-Dist: mypy>=1.7; extra == 'dev'
Requires-Dist: pytest-asyncio>=0.23.0; extra == 'dev'
Requires-Dist: pytest-cov>=4.1.0; extra == 'dev'
Requires-Dist: pytest>=8.0; extra == 'dev'
Requires-Dist: ruff>=0.1.0; extra == 'dev'
Provides-Extra: django
Requires-Dist: django>=5.0; extra == 'django'
Provides-Extra: fastapi
Requires-Dist: fastapi>=0.100.0; extra == 'fastapi'
Requires-Dist: uvicorn>=0.24.0; extra == 'fastapi'
Provides-Extra: flask
Requires-Dist: flask>=3.0; extra == 'flask'
Provides-Extra: pyramid
Requires-Dist: pyramid>=2.0; extra == 'pyramid'
Requires-Dist: waitress>=2.1.2; extra == 'pyramid'
Provides-Extra: solana
Requires-Dist: base58>=2.1.1; extra == 'solana'
Requires-Dist: solana>=0.34.0; extra == 'solana'
Requires-Dist: solders>=0.21.0; extra == 'solana'
Provides-Extra: tests
Requires-Dist: anyio>=4.0.0; extra == 'tests'
Requires-Dist: hexbytes>=0.3.1; extra == 'tests'
Requires-Dist: pytest-asyncio>=0.23.0; extra == 'tests'
Requires-Dist: pytest-django>=4.8.0; extra == 'tests'
Requires-Dist: pytest>=8.0; extra == 'tests'
Requires-Dist: respx>=0.21.1; extra == 'tests'
Requires-Dist: webtest>=3.0.0; extra == 'tests'
Provides-Extra: tornado
Requires-Dist: tornado>=6.0; extra == 'tornado'
